colliery/__init__.py
colliery/__main__.py
colliery_py-0.0.0a0.dist-info/LICENCE
colliery_py-0.0.0a0.dist-info/METADATA
colliery_py-0.0.0a0.dist-info/WHEEL
colliery_py-0.0.0a0.dist-info/entry_points.txt
colliery_py-0.0.0a0.dist-info/top_level.txt
colliery_py-0.0.0a0.dist-info/RECORD
